ipcuy/__init__.py
ipcuy/core.py
ipcuykeh-0.1.0.dist-info/licenses/LICENSE
ipcuykeh-0.1.0.dist-info/METADATA
ipcuykeh-0.1.0.dist-info/WHEEL
ipcuykeh-0.1.0.dist-info/top_level.txt
ipcuykeh-0.1.0.dist-info/RECORD
